m59api/__init__.py
m59api/api.py
m59api/cli.py
m59api/config.py
m59api/main.py
m59api/maintenance.py
m59api-0.2.3.dist-info/METADATA
m59api-0.2.3.dist-info/WHEEL
m59api-0.2.3.dist-info/entry_points.txt
m59api-0.2.3.dist-info/top_level.txt
m59api-0.2.3.dist-info/RECORD
