Metadata-Version: 2.4
Name: m59api
Version: 0.2.3
Summary: A FastAPI-based API for managing Meridian 59 servers with multi-server webhook routing.
Home-page: https://github.com/adrienlaws/m59api
Author: Adrien Laws
Author-email: laws.adrien@gmail.com
Classifier: Programming Language :: Python :: 3
Classifier: Framework :: FastAPI
Classifier: License :: OSI Approved :: MIT License
Classifier: Operating System :: OS Independent
Requires-Python: >=3.7
Requires-Dist: fastapi>=0.70.0
Requires-Dist: uvicorn>=0.15.0
Requires-Dist: httpx>=0.23.0
Dynamic: author
Dynamic: author-email
Dynamic: classifier
Dynamic: description
Dynamic: description-content-type
Dynamic: home-page
Dynamic: requires-dist
Dynamic: requires-python
Dynamic: summary
